rawan_package/MyClass.py
rawan_package/__init__.py
rawan_homework-0.0.1.dist-info/METADATA
rawan_homework-0.0.1.dist-info/WHEEL
rawan_homework-0.0.1.dist-info/top_level.txt
rawan_homework-0.0.1.dist-info/RECORD
